LICENSE
README.md
setup.cfg
setup.py
pylidc/Annotation.py
pylidc/Contour.py
pylidc/Scan.py
pylidc/Zval.py
pylidc/_Base.py
pylidc/__init__.py
pylidc/annotation_distance_metrics.py
pylidc/pylidc.sqlite
pylidc/utils.py
pylidc_updated.egg-info/PKG-INFO
pylidc_updated.egg-info/SOURCES.txt
pylidc_updated.egg-info/dependency_links.txt
pylidc_updated.egg-info/requires.txt
pylidc_updated.egg-info/top_level.txt