Metadata-Version: 2.1
Name: pylidc-updated
Version: 0.2.3
Summary: A library for working with the LIDC dataset. Modified to work with modern numpy
Home-page: https://github.com/faridulreza/pylidc
Author: Matt Hancock
Author-email: not.matt.hancock@gmail.com
License: MIT
Keywords: pylidc LIDC lung sql research
Platform: UNKNOWN
Classifier: Development Status :: 2 - Pre-Alpha
Classifier: Intended Audience :: Healthcare Industry
Classifier: Intended Audience :: Science/Research
Classifier: License :: OSI Approved :: MIT License
Classifier: Operating System :: MacOS
Classifier: Operating System :: POSIX :: Linux
Classifier: Programming Language :: Python :: 2
Classifier: Programming Language :: Python :: 2.7
Classifier: Programming Language :: Python :: 3
Classifier: Programming Language :: Python :: 3.5
Classifier: Topic :: Database
Classifier: Topic :: Scientific/Engineering :: Medical Science Apps.
Classifier: Topic :: Scientific/Engineering :: Visualization
License-File: LICENSE
